odoo8_addon_crm_claim_rma-8.0.1.2.0-py3.8-nspkg.pth
odoo_addons/crm_claim_rma/README.rst
odoo_addons/crm_claim_rma/__init__.py
odoo_addons/crm_claim_rma/__openerp__.py
odoo_addons/crm_claim_rma/data/crm_case_categ.xml
odoo_addons/crm_claim_rma/data/crm_case_section.xml
odoo_addons/crm_claim_rma/data/ir_sequence_type.xml
odoo_addons/crm_claim_rma/demo/account_invoice.xml
odoo_addons/crm_claim_rma/demo/account_invoice_line.xml
odoo_addons/crm_claim_rma/demo/claim_line.xml
odoo_addons/crm_claim_rma/demo/crm_claim.xml
odoo_addons/crm_claim_rma/i18n/am.po
odoo_addons/crm_claim_rma/i18n/ar.po
odoo_addons/crm_claim_rma/i18n/bg.po
odoo_addons/crm_claim_rma/i18n/bs.po
odoo_addons/crm_claim_rma/i18n/ca.po
odoo_addons/crm_claim_rma/i18n/ca_ES.po
odoo_addons/crm_claim_rma/i18n/crm_claim_rma.pot
odoo_addons/crm_claim_rma/i18n/cs.po
odoo_addons/crm_claim_rma/i18n/da.po
odoo_addons/crm_claim_rma/i18n/da_DK.po
odoo_addons/crm_claim_rma/i18n/de.po
odoo_addons/crm_claim_rma/i18n/el_GR.po
odoo_addons/crm_claim_rma/i18n/en_AU.po
odoo_addons/crm_claim_rma/i18n/en_GB.po
odoo_addons/crm_claim_rma/i18n/es.po
odoo_addons/crm_claim_rma/i18n/es_AR.po
odoo_addons/crm_claim_rma/i18n/es_CL.po
odoo_addons/crm_claim_rma/i18n/es_CO.po
odoo_addons/crm_claim_rma/i18n/es_CR.po
odoo_addons/crm_claim_rma/i18n/es_DO.po
odoo_addons/crm_claim_rma/i18n/es_EC.po
odoo_addons/crm_claim_rma/i18n/es_ES.po
odoo_addons/crm_claim_rma/i18n/es_MX.po
odoo_addons/crm_claim_rma/i18n/es_PA.po
odoo_addons/crm_claim_rma/i18n/es_PE.po
odoo_addons/crm_claim_rma/i18n/es_PY.po
odoo_addons/crm_claim_rma/i18n/es_VE.po
odoo_addons/crm_claim_rma/i18n/et.po
odoo_addons/crm_claim_rma/i18n/eu.po
odoo_addons/crm_claim_rma/i18n/eu_ES.po
odoo_addons/crm_claim_rma/i18n/fa.po
odoo_addons/crm_claim_rma/i18n/fi.po
odoo_addons/crm_claim_rma/i18n/fr.po
odoo_addons/crm_claim_rma/i18n/fr_CA.po
odoo_addons/crm_claim_rma/i18n/fr_CH.po
odoo_addons/crm_claim_rma/i18n/fr_FR.po
odoo_addons/crm_claim_rma/i18n/gl.po
odoo8_addon_crm_claim_rma-8.0.1.2.0.dist-info/METADATA
odoo8_addon_crm_claim_rma-8.0.1.2.0.dist-info/WHEEL
odoo8_addon_crm_claim_rma-8.0.1.2.0.dist-info/namespace_packages.txt
odoo8_addon_crm_claim_rma-8.0.1.2.0.dist-info/top_level.txt
odoo8_addon_crm_claim_rma-8.0.1.2.0.dist-info/RECORD
