Metadata-Version: 2.1
Name: odoo8-addon-crm-claim-rma
Version: 8.0.1.2.0
Summary: RMA Claim (Product Return Management)
Home-page: https://odoo-community.org
Author: Akretion, Camptocamp, Eezee-it, MONK Software, Vauxoo, Odoo Community Association (OCA)
Author-email: support@odoo-community.org
License: AGPL-3
Platform: UNKNOWN
Classifier: Programming Language :: Python
Classifier: Framework :: Odoo
Classifier: Framework :: Odoo :: 8.0
Classifier: License :: OSI Approved :: GNU Affero General Public License v3
Requires-Python: ~=2.7
Requires-Dist: odoo8-addon-crm-claim-rma-code
Requires-Dist: odoo8-addon-crm-rma-location
Requires-Dist: odoo8-addon-product-warranty
Requires-Dist: odoo (<9.0a,>=8.0a)
